python_boilerplate/__init__.py
python_boilerplate/cli.py
python_boilerplate/python_boilerplate.py
libcommons-0.1.0.dist-info/AUTHORS.rst
libcommons-0.1.0.dist-info/LICENSE
libcommons-0.1.0.dist-info/METADATA
libcommons-0.1.0.dist-info/WHEEL
libcommons-0.1.0.dist-info/entry_points.txt
libcommons-0.1.0.dist-info/top_level.txt
libcommons-0.1.0.dist-info/RECORD
